README.md
setup.cfg
setup.py
data/__init__.py
data/test_training_dataset.py
data/sample-dataset/__init__.py
message_passing_nn/__init__.py
message_passing_nn/cli.py
message_passing_nn/create_message_passing_nn.py
message_passing_nn.egg-info/PKG-INFO
message_passing_nn.egg-info/PKG-INFO 2
message_passing_nn.egg-info/SOURCES 2.txt
message_passing_nn.egg-info/SOURCES.txt
message_passing_nn.egg-info/dependency_links 2.txt
message_passing_nn.egg-info/dependency_links.txt
message_passing_nn.egg-info/entry_points 2.txt
message_passing_nn.egg-info/entry_points.txt
message_passing_nn.egg-info/requires 2.txt
message_passing_nn.egg-info/requires.txt
message_passing_nn.egg-info/top_level 2.txt
message_passing_nn.egg-info/top_level.txt
message_passing_nn/data/__init__.py
message_passing_nn/data/data_preprocessor.py
message_passing_nn/data/graph_dataset.py
message_passing_nn/data/preprocessor.py
message_passing_nn/fixtures/__init__.py
message_passing_nn/fixtures/characters.py
message_passing_nn/fixtures/filenames.py
message_passing_nn/model/__init__.py
message_passing_nn/model/graph_gru_encoder.py
message_passing_nn/model/graph_rnn_encoder.py
message_passing_nn/model/node.py
message_passing_nn/repository/__init__.py
message_passing_nn/repository/file_system_repository.py
message_passing_nn/repository/repository.py
message_passing_nn/trainer/__init__.py
message_passing_nn/trainer/model_trainer.py
message_passing_nn/usecase/__init__.py
message_passing_nn/usecase/grid_search.py
message_passing_nn/utils/
message_passing_nn/utils/__init__.py
message_passing_nn/utils/grid_search_parameters_parser.py
message_passing_nn/utils/loss_function_selector.py
message_passing_nn/utils/loss_functions.py
message_passing_nn/utils/model_selector.py
message_passing_nn/utils/models.py
message_passing_nn/utils/optimizer_selector.py
message_passing_nn/utils/optimizers.py
message_passing_nn/utils/saver.py
tests/data/__init__.py
tests/data/test_data_preprocessor.py
tests/fixtures/__init__.py
tests/fixtures/loss_functions.py
tests/fixtures/matrices_and_vectors.py
tests/fixtures/optimizers.py
tests/model/__init__.py
tests/model/test_graph_gru_encoder.py
tests/model/test_graph_rnn_ncoder.py
tests/model/test_node.py
tests/repository/__init__.py
tests/repository/test_file_system_repository.py
tests/test_data/__init__.py
tests/test_data/repo-test-data/__init__.py
tests/test_data/training-test-data/__init__.py
tests/trainer/__init__.py
tests/trainer/test_model_trainer.py
tests/usecase/__init__.py
